{"sourceId": "1633", "sourceTitle": "DIE WELT", "sourceUri": "www.welt.de", "articles": [{"categories": [], "date": "2013-12-17", "id": "100376", "isDuplicate": false, "lang": "deu", "sim": 0.5686, "sourceId": "1633", "sourceTitle": "DIE WELT", "sourceUri": "www.welt.de", "storyUri": "b738a3b7-2db3-4d38-88c8-76c4eb4f835b-2340", "time": "15:26:00", "title": "Fu\u00dfball-Bundesliga: Die Demontage der Trainer Slomka und Keller", "uri": "http://www.welt.de/sport/fussball/bundesliga/hannover-96/article123017603/Die-Demontage-der-Trainer-Slomka-und-Keller.html"}, {"categories": [], "date": "2014-04-23", "id": "10102620", "isDuplicate": false, "lang": "deu", "sim": 0.5255, "sourceId": "1633", "sourceTitle": "DIE WELT", "sourceUri": "www.welt.de", "storyUri": "b738a3b7-2db3-4d38-88c8-76c4eb4f835b-91335", "time": "06:20:00", "title": "Schleswig-Holstein: Zahl der Tierversuche im Norden ist gestiegen", "uri": "http://www.welt.de/regionales/hamburg/article127145454/Zahl-der-Tierversuche-im-Norden-ist-gestiegen.html"}, {"categories": [], "date": "2014-04-23", "id": "10104841", "isDuplicate": false, "lang": "deu", "sim": 0.5511, "sourceId": "1633", "sourceTitle": "DIE WELT", "sourceUri": "www.welt.de", "storyUri": "b738a3b7-2db3-4d38-88c8-76c4eb4f835b-90271", "time": "06:17:00", "title": "Viele gibt es im Ruhgebiet: Klassische Automobile in Deutschland", "uri": "http://www.welt.de/motor/news/article127067617/Klassische-Automobile-in-Deutschland.html"}, {"categories": [], "date": "2014-04-23", "id": "10130872", "isDuplicate": false, "lang": "deu", "sim": 0.532, "sourceId": "1633", "sourceTitle": "DIE WELT", "sourceUri": "www.welt.de", "storyUri": "b738a3b7-2db3-4d38-88c8-76c4eb4f835b-90535", "time": "08:21:00", "title": "\"Weltlage\": Putins Strategien wecken schmerzliche Erinnerungen", "uri": "http://www.welt.de/debatte/kolumnen/Lord-Weidenfeld/article126983743/Putins-Strategien-wecken-schmerzliche-Erinnerungen.html"}, {"categories": [], "date": "2013-12-28", "id": "1013918", "isDuplicate": false, "lang": "deu", "sim": 0.417, "sourceId": "1633", "sourceTitle": "DIE WELT", "sourceUri": "www.welt.de", "storyUri": "b738a3b7-2db3-4d38-88c8-76c4eb4f835b-9257", "time": "05:18:00", "title": "F\u00fcr die Mitte der Gesellschaft: Neuheiten-Vorschau 2014: Die Mittelklasse", "uri": "http://www.welt.de/motor/news/article123325096/Neuheiten-Vorschau-2014-Die-Mittelklasse.html"}, {"categories": [], "date": "2013-12-28", "id": "1013920", "isDuplicate": false, "lang": "deu", "sim": 0.6855, "sourceId": "1633", "sourceTitle": "DIE WELT", "sourceUri": "www.welt.de", "storyUri": "b738a3b7-2db3-4d38-88c8-76c4eb4f835b-10850", "time": "05:18:00", "title": "Viel Traktion f\u00fcr wenig Geld : Allradautos unter 20.000 Euro", "uri": "http://www.welt.de/motor/news/article123325094/Allradautos-unter-20-000-Euro.html"}, {"categories": [], "date": "2014-04-23", "id": "10148990", "isDuplicate": false, "lang": "deu", "sim": 0.5133, "sourceId": "1633", "sourceTitle": "DIE WELT", "sourceUri": "www.welt.de", "storyUri": "b738a3b7-2db3-4d38-88c8-76c4eb4f835b-90744", "time": "09:35:00", "title": "Sex-Literatur: \"Sex bei mir ist plakativ - aber sch\u00f6n verpackt\"", "uri": "http://www.welt.de/vermischtes/article127188049/Sex-bei-mir-ist-plakativ-aber-schoen-verpackt.html"}]}